setup.cfg
setup.py
rn2903/__init__.py
rn2903.egg-info/PKG-INFO
rn2903.egg-info/SOURCES.txt
rn2903.egg-info/dependency_links.txt
rn2903.egg-info/not-zip-safe
rn2903.egg-info/top_level.txt
rn2903MAC/__init__.py